{"cameraMode":{"drawMode":0,"name":"Shaded","section":"Shading Mode"},"sceneLighting":true,"audioPlay":false,"sceneViewState":{"showFog":true,"showMaterialUpdate":false,"showSkybox":true,"showFlares":true,"showImageEffects":true,"showParticleSystems":true},"in2DMode":false,"pivot":{"x":0.3342682123184204,"y":3.0746309757232668,"z":16.753250122070314},"rotation":{"x":-0.2853582203388214,"y":-0.14419327676296235,"z":0.04347220063209534,"w":-0.9465142488479614},"size":8.314190864562989,"orthographic":false}